pyftpsyncs3
