Metadata-Version: 2.1
Name: pyftpsync-s3
Version: 0.0.9
Summary: Amazon S3 synchronization target for pyftpsync library
Home-page: https://github.com/pyxnode/pyftpsync-s3
Author: pyxnode
Author-email: pynode@protonmail.com
License: UNKNOWN
Platform: UNKNOWN
Classifier: Programming Language :: Python :: 3
Classifier: License :: OSI Approved :: MIT License
Classifier: Operating System :: OS Independent
